pdgw/__init__.py
pdgw/client.py
pdgw/error.py
pdgw/gateway.py
pdgw/http.py
pdgw/mqtt.py
pdgw/source.py
pdgw-0.3.0.dist-info/METADATA
pdgw-0.3.0.dist-info/WHEEL
pdgw-0.3.0.dist-info/top_level.txt
pdgw-0.3.0.dist-info/RECORD
