Metadata-Version: 2.1
Name: pdgw
Version: 0.3.0
Summary: Particle DataGateway client
Home-page: https://scaleplan.io
Author: ScalePlan Engineering
Author-email: dev@scaleplan.io
License: Proprietary
Keywords: particle,datagateway,cloudevents,scaleplan,cloud,events,event
Platform: UNKNOWN
Classifier: Development Status :: 4 - Beta
Classifier: Intended Audience :: Developers
Classifier: License :: OSI Approved :: Apache Software License
Classifier: Programming Language :: Python :: 3
Classifier: Programming Language :: Python :: 3.6
Classifier: Programming Language :: Python :: 3.7
Classifier: Programming Language :: Python :: 3.8
Classifier: Operating System :: OS Independent
Requires-Dist: spce
Requires-Dist: urllib3
Provides-Extra: avro
Requires-Dist: spce[avro] (>=0.2.0) ; extra == 'avro'
Provides-Extra: mqtt
Requires-Dist: paho-mqtt (>=1.5.1) ; extra == 'mqtt'
